frictionless/__init__.py
frictionless/__main__.py
frictionless/conftest.py
frictionless/exception.py
frictionless/platform.py
frictionless/py.typed
frictionless/settings.py
frictionless/types.py
frictionless/actions/__init__.py
frictionless/actions/convert.py
frictionless/actions/describe.py
frictionless/actions/extract.py
frictionless/actions/index.py
frictionless/actions/list.py
frictionless/actions/transform.py
frictionless/actions/validate.py
frictionless/actions/__spec__/__init__.py
frictionless/actions/__spec__/test_describe.py
frictionless/actions/__spec__/test_extract.py
frictionless/actions/__spec__/test_list.py
frictionless/actions/__spec__/test_transform.py
frictionless/actions/__spec__/test_validate.py
frictionless/analyzer/__init__.py
frictionless/analyzer/analyzer.py
frictionless/analyzer/types.py
frictionless/analyzer/__spec__/__init__.py
frictionless/analyzer/__spec__/test_package.py
frictionless/analyzer/__spec__/test_resource.py
frictionless/assets/profiles/geojson.json
frictionless/assets/profiles/topojson.json
frictionless/assets/templates/checklist.md
frictionless/assets/templates/detector.md
frictionless/assets/templates/dialect.md
frictionless/assets/templates/field-table.md
frictionless/assets/templates/field.md
frictionless/assets/templates/inquiry.md
frictionless/assets/templates/package-table.md
frictionless/assets/templates/package.md
frictionless/assets/templates/pipeline.md
frictionless/assets/templates/report-task.md
frictionless/assets/templates/report.md
frictionless/assets/templates/resource-table.md
frictionless/assets/templates/resource.md
frictionless/assets/templates/schema-table.md
frictionless/assets/templates/schema.md
frictionless/assets/templates/step.md
frictionless/assets/templates/task.md
frictionless/assets/templates/erd/field.html
frictionless/assets/templates/erd/graph.html
frictionless/assets/templates/erd/primary_key_field.html
frictionless/assets/templates/erd/table.html
frictionless/catalog/__init__.py
frictionless-5.17.1.dist-info/METADATA
frictionless-5.17.1.dist-info/WHEEL
frictionless-5.17.1.dist-info/entry_points.txt
frictionless-5.17.1.dist-info/licenses/AUTHORS.md
frictionless-5.17.1.dist-info/licenses/LICENSE.md
frictionless-5.17.1.dist-info/RECORD
